psydapt.cpython-36m-x86_64-linux-gnu.so
psydapt-0.1.3.0.dist-info/LICENSE
psydapt-0.1.3.0.dist-info/WHEEL
psydapt-0.1.3.0.dist-info/METADATA
psydapt-0.1.3.0.dist-info/RECORD
psydapt-0.1.3.0.dist-info/top_level.txt
