Metadata-Version: 2.1
Name: psydapt
Version: 0.1.3.0
Summary: Bindings for psydapt (https://github.com/aforren1/psydapt)
Home-page: https://github.com/aforren1/psydapt-py
Author: Alexander Forrence
Author-email: alex.forrence@gmail.com
License: UNKNOWN
Platform: UNKNOWN
Classifier: License :: OSI Approved :: GNU General Public License v3 or later (GPLv3+)
Classifier: Development Status :: 4 - Beta
Classifier: Intended Audience :: Science/Research
Classifier: Programming Language :: Python :: 3
Classifier: Programming Language :: Python :: 3.6
Classifier: Programming Language :: Python :: 3.7
Classifier: Programming Language :: Python :: 3.8
Classifier: Programming Language :: Python :: 3.9
